oktaauth/__init__.py
oktaauth/main.py
oktaauth/metadata.py
oktaauth/models.py
oktaauth-0.2.dist-info/DESCRIPTION.rst
oktaauth-0.2.dist-info/METADATA
oktaauth-0.2.dist-info/RECORD
oktaauth-0.2.dist-info/WHEEL
oktaauth-0.2.dist-info/entry_points.txt
oktaauth-0.2.dist-info/metadata.json
oktaauth-0.2.dist-info/top_level.txt
