Metadata-Version: 2.0
Name: oktaauth
Version: 0.2
Summary: Authenticates from the CLI
Home-page: https://www.thoughtworks.com/
Author: Peter Gillard-Moss
Author-email: pgillard@thoughtworks.com
License: UNKNOWN
Platform: UNKNOWN
Classifier: Development Status :: 1 - Planning
Classifier: Environment :: Console
Classifier: Intended Audience :: Developers
Classifier: License :: OSI Approved :: Apache Software License
Classifier: Natural Language :: English
Classifier: Operating System :: OS Independent
Classifier: Programming Language :: Python :: 2.6
Classifier: Programming Language :: Python :: 2.7
Classifier: Programming Language :: Python :: 3.3
Classifier: Programming Language :: Python :: Implementation :: PyPy
Classifier: Topic :: Documentation
Classifier: Topic :: Software Development :: Libraries :: Python Modules
Classifier: Topic :: System :: Installation/Setup
Classifier: Topic :: System :: Software Distribution
Requires-Dist: argparse
Requires-Dist: argparse
Requires-Dist: beautifulsoup4 (>=4.4)
Requires-Dist: requests (>=2.8)
